CHANGELOG.md
LICENSE
MANIFEST.in
Makefile
README.md
setup.cfg
setup.py
tox.ini
wc_django_celery_unicall.egg-info/PKG-INFO
wc_django_celery_unicall.egg-info/SOURCES.txt
wc_django_celery_unicall.egg-info/dependency_links.txt
wc_django_celery_unicall.egg-info/requires.txt
wc_django_celery_unicall.egg-info/top_level.txt
wcd_celery_unicall/__init__.py
wcd_celery_unicall/apps.py
wcd_celery_unicall/exceptions.py
wcd_celery_unicall/shortcuts.py
wcd_celery_unicall/task.py
wcd_celery_unicall/utils.py